<beans xmlns="http://www.springframework.org/schema/beans"
    xmlns:xsi="http://www.w3.org/2001/XMLSchema-instance" xmlns:context="http://www.springframework.org/schema/context"
    xmlns:aop="http://www.springframework.org/schema/aop" xmlns:util="http://www.springframework.org/schema/util"
    xmlns:ehcache="http://www.springmodules.org/schema/ehcache" xmlns:p="http://www.springframework.org/schema/p"
    xsi:schemaLocation="http://www.springframework.org/schema/beans http://www.springframework.org/schema/beans/spring-beans-3.1.xsd
    http://www.springframework.org/schema/aop http://www.springframework.org/schema/aop/spring-aop-3.1.xsd
    http://www.springframework.org/schema/util http://www.springframework.org/schema/util/spring-util-3.1.xsd
    http://www.springframework.org/schema/context http://www.springframework.org/schema/context/spring-context-3.1.xsd">

    <context:component-scan base-package="org.esco.portlet.changeetab.web.controller" />
    <context:annotation-config />

    <!-- JSP view resolver -->
    <bean class="org.springframework.web.servlet.view.InternalResourceViewResolver"
          p:prefix="/WEB-INF/jsp/" p:suffix=".jsp" >
          <property name="contentType" value="text/html;charset=UTF-8" />
    </bean>

    <!--
    <bean id="homeController" class="org.esco.portlet.changeetab.web.controller.ChangeEtablissementController" />

    <bean id="portletModeHandlerMapping"
        class="org.springframework.web.portlet.handler.PortletModeHandlerMapping">
        <property name="order" value="20" />
        <property name="portletModeMap">
            <map>
                <entry key="view" value-ref="homeController" />
            </map>
        </property>
    </bean>
     -->

    <!-- Properties configuration -->
    <bean id="propertyConfigurer" class="org.springframework.context.support.PortalPropertySourcesPlaceholderConfigurer">
        <property name="locations">
            <list>
                <value>classpath:configuration.properties</value>
                <!--
                 | The following optional files allow deployers to set or override most
                 | configuration settings in a manner that is outside the footprint of the
                 | build/deploy cycle and SCM.
                 |
                 | Reasons for choosing that may include:
                 |   - Desire to keep sensitive information out of your Git repository
                 |   - Ability to change some common settings without a full build and deploy cycle
                 |   - Building a WAR/EAR that is environment-independent
                 |
                 | Any property defined in the above files that is referenced in the Spring context
                 | may be overridden in one (or both) of these files.  Later files override earlier
                 | files.
                 |
                 | The conventional location of ${portal.home} is ${catalina.base}/portal;  but you
                 | can (typically) override that location using a PORTAL_HOME environment variable.
                 | (Ultimately it depends on your setenv.sh or setenv.bat file.)
                 |
                 | The first file (global.properties) may contain properties that are shared with
                 | other modules (e.g. portlets) in Tomcat.  Several Apereo portlets source
                 | global.properties automatically.  The second file (simple-cms.properties) is
                 | (should be) sourced by this module exclusively.
                 +-->
                <value>file:${portal.home}/global.properties</value>
                <value>file:${portal.home}/change-etablissement-portlet.properties</value>
            </list>
        </property>
    </bean>

</beans>